paddle_sparse_dense/__init__.py
paddle_sparse_dense/batching.py
paddle_sparse_dense/sparse.py
paddle_sparse_dense/spgemm.py
paddle_sparse_dense/utils.py
paddle_sparse_dense-0.0.5.dist-info/LICENSE
paddle_sparse_dense-0.0.5.dist-info/METADATA
paddle_sparse_dense-0.0.5.dist-info/WHEEL
paddle_sparse_dense-0.0.5.dist-info/top_level.txt
paddle_sparse_dense-0.0.5.dist-info/RECORD
