Metadata-Version: 2.1
Name: paddle-sparse-dense
Version: 0.0.5
Summary: Sparse-dense operators for paddle.
Home-page: https://github.com/eliphatfs/paddle-sparse-dense
Author: flandre.info
Author-email: flandre@scarletx.cn
License: UNKNOWN
Platform: UNKNOWN
Classifier: Programming Language :: Python :: 3 :: Only
Classifier: License :: OSI Approved :: Apache Software License
Classifier: Operating System :: OS Independent
Requires-Python: ~=3.6
